README.md
setup.py
sklearn_dummies/__init__.py
sklearn_dummies/base.py
sklearn_dummies.egg-info/PKG-INFO
sklearn_dummies.egg-info/SOURCES.txt
sklearn_dummies.egg-info/dependency_links.txt
sklearn_dummies.egg-info/requires.txt
sklearn_dummies.egg-info/top_level.txt